usearch-2.23.0.dist-info/RECORD
usearch-2.23.0.dist-info/WHEEL
usearch-2.23.0.dist-info/top_level.txt
usearch-2.23.0.dist-info/METADATA
usearch-2.23.0.dist-info/licenses/LICENSE
usearch/server.py
usearch/index.py
usearch/numba.py
usearch/client.py
usearch/io.py
usearch/__init__.py
usearch/compiled.cpython-314t-darwin.so
usearch/py.typed
usearch/eval.py
