Metadata-Version: 2.1
Name: usearch
Version: 2.23.0
Summary: Smaller & Faster Single-File Vector Search Engine from Unum
Home-page: https://github.com/unum-cloud/usearch
Author: Ash Vardanian
Author-email: info@unum.cloud
License: Apache-2.0
Classifier: Development Status :: 5 - Production/Stable
Classifier: Natural Language :: English
Classifier: Intended Audience :: Developers
Classifier: Intended Audience :: Information Technology
Classifier: License :: OSI Approved :: Apache Software License
Classifier: Programming Language :: C++
Classifier: Programming Language :: Python :: 3 :: Only
Classifier: Programming Language :: Python :: Implementation :: CPython
Classifier: Programming Language :: Java
Classifier: Programming Language :: JavaScript
Classifier: Programming Language :: Objective C
Classifier: Programming Language :: Rust
Classifier: Programming Language :: Other
Classifier: Operating System :: MacOS
Classifier: Operating System :: Unix
Classifier: Operating System :: Microsoft :: Windows
Classifier: Topic :: System :: Clustering
Classifier: Topic :: Database :: Database Engines/Servers
Classifier: Topic :: Scientific/Engineering :: Artificial Intelligence
License-File: LICENSE
Requires-Dist: numpy
Requires-Dist: tqdm
